CHANGES.txt
LICENSE.txt
MANIFEST.in
README.txt
setup.py
Projy.egg-info/PKG-INFO
Projy.egg-info/SOURCES.txt
Projy.egg-info/dependency_links.txt
Projy.egg-info/requires.txt
Projy.egg-info/top_level.txt
bin/projy
docs/Makefile
docs/changelog.rst
docs/conf.py
docs/extend.rst
docs/index.rst
docs/install.rst
docs/make.bat
docs/templates.rst
docs/usage.rst
docs/_build/Projy-0.4.1.zip
docs/_build/doctrees/changelog.doctree
docs/_build/doctrees/environment.pickle
docs/_build/doctrees/extend.doctree
docs/_build/doctrees/index.doctree
docs/_build/doctrees/install.doctree
docs/_build/doctrees/templates.doctree
docs/_build/doctrees/usage.doctree
docs/_build/html/.buildinfo
docs/_build/html/changelog.html
docs/_build/html/extend.html
docs/_build/html/genindex.html
docs/_build/html/index.html
docs/_build/html/install.html
docs/_build/html/objects.inv
docs/_build/html/search.html
docs/_build/html/searchindex.js
docs/_build/html/templates.html
docs/_build/html/usage.html
docs/_build/html/_downloads/AGPL3FileTemplate.txt
docs/_build/html/_downloads/ApacheLicenseFileTemplate.txt
docs/_build/html/_downloads/AuthorCollector.py
docs/_build/html/_downloads/AuthorMailCollector.py
docs/_build/html/_downloads/BSDLicenseFileTemplate.txt
docs/_build/html/_downloads/BibTeXFileTemplate.txt
docs/_build/html/_downloads/BootstrapScriptFileTemplate.txt
docs/_build/html/_downloads/DWTFYWTPLFileTemplate.txt
docs/_build/html/_downloads/DjangoFabfileTemplate.txt
docs/_build/html/_downloads/DjangoGitignoreTemplate.txt
docs/_build/html/_downloads/DjangoMakefileTemplate.txt
docs/_build/html/_downloads/DjangoNginxConfTemplate.txt
docs/_build/html/_downloads/DjangoProjectTemplate.py
docs/_build/html/_downloads/DjangoRequirementsBaseTemplate.txt
docs/_build/html/_downloads/DjangoRequirementsDevTemplate.txt
docs/_build/html/_downloads/DjangoRequirementsProdTemplate.txt
docs/_build/html/_downloads/DjangoSettingsDevTemplate.txt
docs/_build/html/_downloads/DjangoSettingsProdTemplate.txt
docs/_build/html/_downloads/DjangoSupervisorConfTemplate.txt
docs/_build/html/_downloads/FabfileFileTemplate.txt
docs/_build/html/_downloads/GPL2FileTemplate.txt
